lloyd/__init__.py
lloyd/core1.py
lloyd/core2.py
lloyd_python-0.1.1.dist-info/METADATA
lloyd_python-0.1.1.dist-info/WHEEL
lloyd_python-0.1.1.dist-info/entry_points.txt
lloyd_python-0.1.1.dist-info/top_level.txt
lloyd_python-0.1.1.dist-info/RECORD
