Metadata-Version: 2.4
Name: lloyd-python
Version: 0.1.1
Summary: # Lloyd-Python
Author: Your Name
Requires-Python: >=3.6
Dynamic: author
Dynamic: description
Dynamic: description-content-type
Dynamic: requires-python
Dynamic: summary
